README.md
setup.py
data_structures/__init__.py
skbu_2nd_sem.egg-info/PKG-INFO
skbu_2nd_sem.egg-info/SOURCES.txt
skbu_2nd_sem.egg-info/dependency_links.txt
skbu_2nd_sem.egg-info/top_level.txt