Metadata-Version: 2.1
Name: skbu-2nd-sem
Version: 1.0.1
Summary: A Python package for implementing data structures and algorithms for SKBU 2nd semester syllabus.
Home-page: https://github.com/PB2204/SKBU-2nd-Sem
Author: Pabitra Banerjee
Author-email: pabitra.banerjee@explorecode.live
Classifier: Programming Language :: Python :: 3
Classifier: License :: OSI Approved :: MIT License
Classifier: Operating System :: OS Independent
